knazin
