Metadata-Version: 1.0
Name: knazin
Version: 0.2
Summary: Knazin package
Home-page: http://github.com/knazin/package
Author: Kacper Knaz
Author-email: knazkacper@gmail.com
License: GNU
Platform: UNKNOWN
